LICENSE
MANIFEST.in
README.md
pyproject.toml
setup.py
BBA.egg-info/PKG-INFO
BBA.egg-info/SOURCES.txt
BBA.egg-info/dependency_links.txt
BBA.egg-info/top_level.txt
bba/__init__.py
bba/client.py
bba/errors.py
bba/objects.py